aioauth/__init__.py
aioauth/collections.py
aioauth/config.py
aioauth/constances.py
aioauth/errors.py
aioauth/grant_type.py
aioauth/models.py
aioauth/py.typed
aioauth/requests.py
aioauth/response_type.py
aioauth/responses.py
aioauth/server.py
aioauth/storage.py
aioauth/types.py
aioauth/utils.py
aioauth/oidc/__init__.py
aioauth/oidc/core/__init__.py
aioauth/oidc/core/grant_type.py
aioauth/oidc/core/requests.py
aioauth/oidc/core/responses.py
aioauth-2.0.0.dist-info/licenses/LICENSE
aioauth-2.0.0.dist-info/METADATA
aioauth-2.0.0.dist-info/WHEEL
aioauth-2.0.0.dist-info/top_level.txt
aioauth-2.0.0.dist-info/RECORD
