Metadata-Version: 2.4
Name: aioauth
Version: 2.0.0
Summary: Asynchronous OAuth 2.0 framework for Python 3.
Author-email: Ali Aliyev <ali@aliev.me>
Project-URL: homepage, https://github.com/aliev/aioauth
Classifier: Intended Audience :: Information Technology
Classifier: Intended Audience :: System Administrators
Classifier: Operating System :: OS Independent
Classifier: Programming Language :: Python :: 3
Classifier: Programming Language :: Python
Classifier: Topic :: Internet
Classifier: Topic :: Software Development :: Libraries :: Application Frameworks
Classifier: Topic :: Software Development :: Libraries :: Python Modules
Classifier: Topic :: Software Development :: Libraries
Classifier: Topic :: Software Development
Classifier: Typing :: Typed
Classifier: Development Status :: 1 - Planning
Classifier: Environment :: Web Environment
Classifier: Framework :: AsyncIO
Classifier: Intended Audience :: Developers
Classifier: License :: OSI Approved :: MIT License
Classifier: Programming Language :: Python :: 3 :: Only
Classifier: Programming Language :: Python :: 3.7
Classifier: Programming Language :: Python :: 3.8
Classifier: Programming Language :: Python :: 3.9
Classifier: Programming Language :: Python :: 3.10
Classifier: Topic :: Internet :: WWW/HTTP :: HTTP Servers
Classifier: Topic :: Internet :: WWW/HTTP
Requires-Python: >=3.9.0
License-File: LICENSE
Requires-Dist: typing_extensions
Provides-Extra: dev
Requires-Dist: build; extra == "dev"
Requires-Dist: twine; extra == "dev"
Requires-Dist: pytest; extra == "dev"
Requires-Dist: coverage; extra == "dev"
Requires-Dist: pytest-asyncio; extra == "dev"
Requires-Dist: mypy; extra == "dev"
Requires-Dist: bandit; extra == "dev"
Requires-Dist: pre-commit; extra == "dev"
Requires-Dist: pytest-cov; extra == "dev"
Provides-Extra: docs
Requires-Dist: mkdocs; extra == "docs"
Requires-Dist: mkdocs-material; extra == "docs"
Requires-Dist: mkdocstrings[python]; extra == "docs"
Provides-Extra: fastapi
Requires-Dist: aioauth-fastapi>=0.0.1; extra == "fastapi"
Dynamic: license-file
